ultraml/__init__.py
ultraml/core/__init__.py
ultraml/core/extract.py
ultraml-0.1.2.dist-info/LICENSE
ultraml-0.1.2.dist-info/METADATA
ultraml-0.1.2.dist-info/WHEEL
ultraml-0.1.2.dist-info/entry_points.txt
ultraml-0.1.2.dist-info/top_level.txt
ultraml-0.1.2.dist-info/RECORD
