Metadata-Version: 2.1
Name: ultraml
Version: 0.1.2
Summary: A simple package for preprocessing ultrasound imaging data for machine learning
Home-page: https://github.com/stan-hua/ultraml
Author: Stanley Bryan Zamora Hua
Author-email: stanley.z.hua@gmail.com
Classifier: Programming Language :: Python :: 3
Classifier: License :: OSI Approved :: MIT License
Classifier: Operating System :: OS Independent
License-File: LICENSE
Requires-Dist: fire
Requires-Dist: opencv-python
Requires-Dist: numpy
Requires-Dist: scikit-learn
Requires-Dist: tqdm
